formulator/__init__.py
formulator/__main__.py
formulator/conf.py
formulator/enforcer.py
formulator/ferry.py
formulator/meta.py
formulator/nodes.py
formulator/terrors.py
formulator/validation.py
formulator-0.1.2.dist-info/DESCRIPTION.rst
formulator-0.1.2.dist-info/METADATA
formulator-0.1.2.dist-info/RECORD
formulator-0.1.2.dist-info/WHEEL
formulator-0.1.2.dist-info/metadata.json
formulator-0.1.2.dist-info/top_level.txt
